ninam/__init__.py
ninam/__main__.py
ninam-1.0.1.dist-info/METADATA
ninam-1.0.1.dist-info/WHEEL
ninam-1.0.1.dist-info/entry_points.txt
ninam-1.0.1.dist-info/licenses/LICENSE
ninam-1.0.1.dist-info/RECORD
